fastclasses_json/__init__.py
fastclasses_json/api.py
fastclasses_json/core.py
fastclasses_json/mypy_plugin.py
fastclasses_json/py.typed
fastclasses_json/utils.py
fastclasses_json-0.8.0.dist-info/LICENSE.txt
fastclasses_json-0.8.0.dist-info/METADATA
fastclasses_json-0.8.0.dist-info/WHEEL
fastclasses_json-0.8.0.dist-info/top_level.txt
fastclasses_json-0.8.0.dist-info/RECORD
