Metadata-Version: 2.1
Name: fastclasses-json
Version: 0.8.0
Summary: Quickly serialize dataclasses to and from JSON
Home-page: https://github.com/cakemanny/fastclasses-json
Author: Daniel Golding
License: MIT
Project-URL: Bug Tracker, https://github.com/cakemanny/fastclasses-json/issues
Keywords: fast dataclasses json fastclasses
Classifier: Programming Language :: Python :: 3
Classifier: Programming Language :: Python :: 3.8
Classifier: Programming Language :: Python :: 3.9
Classifier: Programming Language :: Python :: 3.10
Classifier: Programming Language :: Python :: 3.11
Classifier: Programming Language :: Python :: 3.12
Classifier: Programming Language :: Python :: 3.13
Classifier: License :: OSI Approved :: MIT License
Classifier: Operating System :: OS Independent
Classifier: Intended Audience :: Developers
Classifier: Development Status :: 4 - Beta
Requires-Python: >=3.8
License-File: LICENSE.txt
Provides-Extra: dev
Requires-Dist: pytest; extra == "dev"
Requires-Dist: flake8; extra == "dev"
Requires-Dist: mypy; extra == "dev"
